stately/__init__.py
stately-0.1.0.dist-info/DESCRIPTION.rst
stately-0.1.0.dist-info/METADATA
stately-0.1.0.dist-info/RECORD
stately-0.1.0.dist-info/WHEEL
stately-0.1.0.dist-info/metadata.json
stately-0.1.0.dist-info/top_level.txt
